supervisor/__init__.py
supervisor/example.py
supervisor/message_handlers.py
supervisor/models.py
supervisor/version.py
ugrc_supervisor-3.2.0.dist-info/licenses/LICENSE
ugrc_supervisor-3.2.0.dist-info/METADATA
ugrc_supervisor-3.2.0.dist-info/WHEEL
ugrc_supervisor-3.2.0.dist-info/top_level.txt
ugrc_supervisor-3.2.0.dist-info/zip-safe
ugrc_supervisor-3.2.0.dist-info/RECORD
