Metadata-Version: 2.4
Name: ugrc-supervisor
Version: 3.2.0
Summary: A watchdog module for scheduled scripts that sends notifications, including any uncaught exceptions.
Home-page: https://github.com/agrc/supervisor
Author: UGRC
Author-email: ugrc-developers@utah.gov
License: MIT
Project-URL: Issue Tracker, https://github.com/agrc/supervisor/issues
Keywords: gis
Classifier: Development Status :: 5 - Production/Stable
Classifier: Intended Audience :: Developers
Classifier: Topic :: Utilities
License-File: LICENSE
Requires-Dist: sendgrid==6.*
Provides-Extra: tests
Requires-Dist: pytest-cov==6.*; extra == "tests"
Requires-Dist: pytest-instafail==0.5.*; extra == "tests"
Requires-Dist: pytest-mock==3.*; extra == "tests"
Requires-Dist: pytest-watch==4.*; extra == "tests"
Requires-Dist: pytest==8.*; extra == "tests"
Requires-Dist: ruff==0.*; extra == "tests"
Dynamic: author
Dynamic: author-email
Dynamic: classifier
Dynamic: home-page
Dynamic: keywords
Dynamic: license
Dynamic: license-file
Dynamic: project-url
Dynamic: provides-extra
Dynamic: requires-dist
Dynamic: summary
